{
    "zabbix_export": {
        "date": "2015-12-03T21:46:03Z",
        "templates": [
            {
                "templates": [],
                "name": "t_vm_zone_dataset",
                "macros": [],
                "items": [],
                "screens": [],
                "applications": [
                    {
                        "name": "ZFS datasets"
                    }
                ],
                "discovery_rules": [
                    {
                        "username": "",
                        "snmpv3_contextname": "",
                        "snmpv3_authpassphrase": "",
                        "snmp_oid": "",
                        "snmpv3_securitylevel": "0",
                        "port": "",
                        "lifetime": "1",
                        "graph_prototypes": [
                            {
                                "show_3d": "0",
                                "graph_items": [
                                    {
                                        "calc_fnc": "2",
                                        "color": "0000C8",
                                        "item": {
                                            "host": "t_vm_zone_dataset",
                                            "key": "kstat.get[unix:0:vopstats_{#DEV}:write_bytes]"
                                        },
                                        "sortorder": "2",
                                        "drawtype": "5",
                                        "type": "0",
                                        "yaxisside": "1"
                                    },
                                    {
                                        "calc_fnc": "2",
                                        "color": "00C800",
                                        "item": {
                                            "host": "t_vm_zone_dataset",
                                            "key": "kstat.get[unix:0:vopstats_{#DEV}:nread]"
                                        },
                                        "sortorder": "1",
                                        "drawtype": "0",
                                        "type": "0",
                                        "yaxisside": "0"
                                    },
                                    {
                                        "calc_fnc": "2",
                                        "color": "C80000",
                                        "item": {
                                            "host": "t_vm_zone_dataset",
                                            "key": "kstat.get[unix:0:vopstats_{#DEV}:read_bytes]"
                                        },
                                        "sortorder": "0",
                                        "drawtype": "5",
                                        "type": "0",
                                        "yaxisside": "1"
                                    },
                                    {
                                        "calc_fnc": "2",
                                        "color": "C800C8",
                                        "item": {
                                            "host": "t_vm_zone_dataset",
                                            "key": "kstat.get[unix:0:vopstats_{#DEV}:nwrite]"
                                        },
                                        "sortorder": "3",
                                        "drawtype": "0",
                                        "type": "0",
                                        "yaxisside": "0"
                                    }
                                ],
                                "ymin_type_1": "0",
                                "name": "{#MOUNTPOINT} I/O",
                                "percent_left": "0.0000",
                                "type": "0",
                                "ymax_type_1": "0",
                                "height": "200",
                                "yaxismax": "100.0000",
                                "width": "900",
                                "show_legend": "1",
                                "show_work_period": "1",
                                "ymax_item_1": "0",
                                "ymin_item_1": "0",
                                "show_triggers": "1",
                                "yaxismin": "0.0000",
                                "percent_right": "0.0000"
                            }
                        ],
                        "trigger_prototypes": [],
                        "item_prototypes": [
                            {
                                "username": "",
                                "snmpv3_contextname": "",
                                "inventory_link": "0",
                                "multiplier": "0",
                                "trends": "365",
                                "snmpv3_authpassphrase": "",
                                "snmp_oid": "",
                                "snmpv3_securitylevel": "0",
                                "port": "",
                                "logtimefmt": "",
                                "delay": "30",
                                "publickey": "",
                                "params": "",
                                "snmpv3_securityname": "",
                                "formula": "1",
                                "type": "0",
                                "snmpv3_authprotocol": "0",
                                "valuemap": [],
                                "ipmi_sensor": "",
                                "status": "0",
                                "authtype": "0",
                                "snmp_community": "",
                                "description": "",
                                "data_type": "0",
                                "delay_flex": "",
                                "units": "Bps",
                                "value_type": "0",
                                "key": "kstat.get[unix:0:vopstats_{#DEV}:read_bytes]",
                                "delta": "1",
                                "password": "",
                                "snmpv3_privpassphrase": "",
                                "snmpv3_privprotocol": "0",
                                "name": "{#MOUNTPOINT} read bytes",
                                "applications": [
                                    {
                                        "name": "ZFS datasets"
                                    }
                                ],
                                "privatekey": "",
                                "allowed_hosts": "",
                                "history": "7"
                            },
                            {
                                "username": "",
                                "snmpv3_contextname": "",
                                "inventory_link": "0",
                                "multiplier": "0",
                                "trends": "365",
                                "snmpv3_authpassphrase": "",
                                "snmp_oid": "",
                                "snmpv3_securitylevel": "0",
                                "port": "",
                                "logtimefmt": "",
                                "delay": "30",
                                "publickey": "",
                                "params": "",
                                "snmpv3_securityname": "",
                                "formula": "1",
                                "type": "0",
                                "snmpv3_authprotocol": "0",
                                "valuemap": [],
                                "ipmi_sensor": "",
                                "status": "0",
                                "authtype": "0",
                                "snmp_community": "",
                                "description": "",
                                "data_type": "0",
                                "delay_flex": "",
                                "units": "ops",
                                "value_type": "0",
                                "key": "kstat.get[unix:0:vopstats_{#DEV}:nread]",
                                "delta": "1",
                                "password": "",
                                "snmpv3_privpassphrase": "",
                                "snmpv3_privprotocol": "0",
                                "name": "{#MOUNTPOINT} read operations",
                                "applications": [
                                    {
                                        "name": "ZFS datasets"
                                    }
                                ],
                                "privatekey": "",
                                "allowed_hosts": "",
                                "history": "7"
                            },
                            {
                                "username": "",
                                "snmpv3_contextname": "",
                                "inventory_link": "0",
                                "multiplier": "0",
                                "trends": "365",
                                "snmpv3_authpassphrase": "",
                                "snmp_oid": "",
                                "snmpv3_securitylevel": "0",
                                "port": "",
                                "logtimefmt": "",
                                "delay": "30",
                                "publickey": "",
                                "params": "",
                                "snmpv3_securityname": "",
                                "formula": "1",
                                "type": "0",
                                "snmpv3_authprotocol": "0",
                                "valuemap": [],
                                "ipmi_sensor": "",
                                "status": "0",
                                "authtype": "0",
                                "snmp_community": "",
                                "description": "",
                                "data_type": "0",
                                "delay_flex": "",
                                "units": "Bps",
                                "value_type": "0",
                                "key": "kstat.get[unix:0:vopstats_{#DEV}:write_bytes]",
                                "delta": "1",
                                "password": "",
                                "snmpv3_privpassphrase": "",
                                "snmpv3_privprotocol": "0",
                                "name": "{#MOUNTPOINT} write bytes",
                                "applications": [
                                    {
                                        "name": "ZFS datasets"
                                    }
                                ],
                                "privatekey": "",
                                "allowed_hosts": "",
                                "history": "7"
                            },
                            {
                                "username": "",
                                "snmpv3_contextname": "",
                                "inventory_link": "0",
                                "multiplier": "0",
                                "trends": "365",
                                "snmpv3_authpassphrase": "",
                                "snmp_oid": "",
                                "snmpv3_securitylevel": "0",
                                "port": "",
                                "logtimefmt": "",
                                "delay": "30",
                                "publickey": "",
                                "params": "",
                                "snmpv3_securityname": "",
                                "formula": "1",
                                "type": "0",
                                "snmpv3_authprotocol": "0",
                                "valuemap": [],
                                "ipmi_sensor": "",
                                "status": "0",
                                "authtype": "0",
                                "snmp_community": "",
                                "description": "",
                                "data_type": "0",
                                "delay_flex": "",
                                "units": "ops",
                                "value_type": "0",
                                "key": "kstat.get[unix:0:vopstats_{#DEV}:nwrite]",
                                "delta": "1",
                                "password": "",
                                "snmpv3_privpassphrase": "",
                                "snmpv3_privprotocol": "0",
                                "name": "{#MOUNTPOINT} write operations",
                                "applications": [
                                    {
                                        "name": "ZFS datasets"
                                    }
                                ],
                                "privatekey": "",
                                "allowed_hosts": "",
                                "history": "7"
                            }
                        ],
                        "delay": "3600",
                        "publickey": "",
                        "params": "",
                        "snmpv3_securityname": "",
                        "type": "0",
                        "snmpv3_authprotocol": "0",
                        "status": "0",
                        "authtype": "0",
                        "snmp_community": "",
                        "description": "",
                        "host_prototypes": [],
                        "delay_flex": "",
                        "key": "zone.dataset.discovery[{HOST.HOST}]",
                        "ipmi_sensor": "",
                        "password": "",
                        "snmpv3_privpassphrase": "",
                        "snmpv3_privprotocol": "0",
                        "name": "Zone ZFS dataset discovery",
                        "privatekey": "",
                        "filter": ":",
                        "allowed_hosts": ""
                    }
                ],
                "groups": [
                    {
                        "name": "Templates"
                    }
                ],
                "template": "t_vm_zone_dataset"
            }
        ],
        "version": "2.0",
        "groups": [
            {
                "name": "Templates"
            }
        ]
    }
}
